talkcode/__init__.py
talkcode/main.py
talkcode/analyzer/chunk_search.py
talkcode/analyzer/embeddings.py
talkcode/analyzer/flow.py
talkcode/analyzer/indexer.py
talkcode/analyzer/parser.py
talkcode/chat/ai.py
talkcode/chat/cli.py
talkcode/chat/prompts.py
talkcode/core/cache.py
talkcode/core/config.py
talkcode/core/utils.py
talkcode/decorators/__init__.py
talkcode/decorators/trace.py
talkcode/ui/app.py
talkcode-0.1.0.dist-info/licenses/LICENSE
talkcode-0.1.0.dist-info/METADATA
talkcode-0.1.0.dist-info/WHEEL
talkcode-0.1.0.dist-info/entry_points.txt
talkcode-0.1.0.dist-info/top_level.txt
talkcode-0.1.0.dist-info/RECORD
