Metadata-Version: 2.4
Name: talkcode
Version: 0.1.0
Summary: talkcode: Talk to your codebase using AI and static analysis.
Author-email: Sakshi <spsakshi6@gmail.com>
License: MIT License
Keywords: static analysis,code search,AI,chatbot,textual,legacy code
Classifier: Programming Language :: Python :: 3
Classifier: License :: OSI Approved :: MIT License
Classifier: Operating System :: OS Independent
Classifier: Topic :: Software Development :: Code Generators
Classifier: Intended Audience :: Developers
Requires-Python: >=3.8
License-File: LICENSE
Requires-Dist: openai
Requires-Dist: anthropic
Requires-Dist: google-generativeai
Requires-Dist: rich
Requires-Dist: typer
Requires-Dist: textual>=0.40.0
Requires-Dist: prompt_toolkit
Requires-Dist: toml
Provides-Extra: dev
Requires-Dist: pytest; extra == "dev"
Dynamic: license-file
